MANIFEST.in
README.md
config.json
requirements.txt
setup.cfg
setup.py
Kuyil/__init__.py
Kuyil/database.py
Kuyil.egg-info/PKG-INFO
Kuyil.egg-info/SOURCES.txt
Kuyil.egg-info/dependency_links.txt
Kuyil.egg-info/requires.txt
Kuyil.egg-info/top_level.txt
Kuyil/api/__init__.py
Kuyil/api/dataset.py
Kuyil/api/repository.py
Kuyil/models/__init__.py
Kuyil/models/base.py
Kuyil/models/dataset_entity.py
Kuyil/models/repository_entity.py
Kuyil/repository_client/__init__.py
Kuyil/repository_client/repository_client_helper.py
Kuyil/utils/__init__.py
Kuyil/utils/date_time_util.py
tests/__init__.py
tests/test_database.py
tests/test_dataset.py
tests/test_repository.py