Metadata-Version: 1.0
Name: Kuyil
Version: 0.4
Summary: sprint 1 rc
Home-page: https://github.com/4info/Kuyil
Author: rohitash
Author-email: rohitash@sigmoid.com
License: BSD
Platform: UNKNOWN
